<?xml version="1.0" encoding="utf-8"?>
<RECORD>
<GOID>422225372</GOID>
<Obj>
<SourceRollupType>Newspapers</SourceRollupType>
<ObjectTypes>
<other ObjectTypeOrigin="Publisher">News</other>
<mstar>News</mstar>
</ObjectTypes>
<ObjectRollupType>Articles - All Types</ObjectRollupType>
<TitleAtt>
<Title>WESTERN CONFERENCE PLAYOFFS; Hornets put the Mavericks in familiar spot</Title>
</TitleAtt>
<NumericDate>2008-04-28</NumericDate>
<StartDate>2008-04-28</StartDate>
<EndDate>2008-04-28</EndDate>
<AlphaDate>Apr 28, 2008</AlphaDate>
<Language>
<RawLang>English</RawLang>
</Language>
<Language IsPrimary="true">
<ISO>
<ISOCode>ENG</ISOCode>
<ISOExpansion ISOCode="ENG">English</ISOExpansion>
</ISO>
</Language>
<Copyright>
<CopyrightData>(Copyright (c) 2008 Los Angeles Times)</CopyrightData>
</Copyright>
<PrintLocation>
<StartPage>D.4</StartPage>
<Pagination>D.4</Pagination>
<DocSection>Sports; Part D; Sports Desk</DocSection>
<DocEdition>HOME EDITION</DocEdition>
</PrintLocation>
<ObjectIDs>
<ObjectID IDOrigin="PQ">
<DOCID>1469193251</DOCID>
</ObjectID>
<ObjectID IDOrigin="PQ">
<PCID>39005911</PCID>
</ObjectID>
<ObjectID IDOrigin="PQ">
<PMID>7683</PMID>
</ObjectID>
<ObjectID>
<ProvJournalCode>ANGE</ProvJournalCode>
</ObjectID>
<ObjectID IDOrigin="DTI">
<PublisherXID>LATM080021479</PublisherXID>
</ObjectID>
</ObjectIDs>
<LexileScore>1440</LexileScore>
<Contributors>
<Contributor ContribOrder="1">
<Author>
<NormalizedDisplayForm>Anonymous</NormalizedDisplayForm>
<ContribPersonNameAtt ContribOrigin="AuthorNormalization" IsNormalized="true">
<ContribPersonName>Anonymous</ContribPersonName>
</ContribPersonNameAtt>
<LastNameAtt ContribOrigin="AuthorNormalization" IsNormalized="true">
<LastName>Anonymous</LastName>
</LastNameAtt>
<OriginalFormAtt ContribOrigin="pqauth">
<OriginalForm>Anonymous</OriginalForm>
</OriginalFormAtt>
</Author>
</Contributor>
</Contributors>
<Terms>
<CompanyTerm PndxHeader="true" TermSource="ABI">
<CompanyNameAtt>
<CompanyName>Dallas Mavericks</CompanyName>
</CompanyNameAtt>
<CompanyNAICAtt>
<CompanyNAIC>711211</CompanyNAIC>
</CompanyNAICAtt>
</CompanyTerm>
<GenSubjTerm PndxHeader="true" TermSource="ABI">
<GenSubjValue>Professional basketball</GenSubjValue>
</GenSubjTerm>
<GenSubjTerm PndxHeader="true" TermSource="ABI">
<GenSubjValue>Athletes</GenSubjValue>
</GenSubjTerm>
</Terms>
<Abstract>
<Medium WordCount="106">
<AbsText HTMLContent="true">          &lt;html&gt;            &lt;head&gt;              &lt;meta name="ValidationSchema" content="http://www.w3.org/2002/08/xhtml/xhtml1-strict.xsd"/&gt;              &lt;title/&gt;            &lt;/head&gt;            &lt;body&gt;              &lt;p&gt;West let out his pent-up frustration over a poor Game 3 with a determined effort in Game 4, scoring 10 of his 24 points in a quick stretch early in the second half to help the New Orleans Hornets pull away for a 97-84 victory Sunday and a 3-1 lead in the best-of-seven Western Conference first-round series that put the Mavericks on the brink of a second straight early exit.  Boris Diaw, starting in place of Grant Hill (abdominal strain), had 20 points, 10 rebounds and eight assists to help the Suns avoid a first-round sweep in the series, which the Spurs now lead, 3-1. &lt;/p&gt;            &lt;/body&gt;          &lt;/html&gt;</AbsText>
</Medium>
</Abstract>
<LegacyDataMapping>
<MappingVersion>$Header: $</MappingVersion>
</LegacyDataMapping>
</Obj>
<TextInfo>
<Text HTMLContent="true" WordCount="594">&lt;html&gt;            &lt;head&gt;              &lt;meta name="ValidationSchema" content="http://www.w3.org/2002/08/xhtml/xhtml1-strict.xsd"/&gt;              &lt;title/&gt;            &lt;/head&gt;            &lt;body&gt;              &lt;p&gt;David West hardly said a word the last two days. That meant trouble for the Dallas Mavericks.&lt;/p&gt;              &lt;p&gt;West let out his pent-up frustration over a poor Game 3 with a determined effort in Game 4, scoring 10 of his 24 points in a quick stretch early in the second half to help the New Orleans Hornets pull away for a 97-84 victory Sunday and a 3-1 lead in the best-of-seven Western Conference first-round series that put the Mavericks on the brink of a second straight early exit.&lt;/p&gt;              &lt;p&gt;"Everything was stirring up in him," Coach Byron Scott said of West who had 14 points on six-of-20 shooting in Game 3. "He wasn't going to play the way he played in Game 3. We were banking on that. He was in an aggressive mind-set from the start and he came up big."&lt;/p&gt;              &lt;p&gt;The Hornets hadn't won in Dallas over 14 tries since January 1998. This victory means they might not have to come back until next season. They can eliminate the Mavericks by winning Game 5 Tuesday night in New Orleans.&lt;/p&gt;              &lt;p&gt;Dirk Nowitzki had 22 points and 13 rebounds and Jason Terry scored 20 points, but they didn't get much help. Josh Howard made only three of 16 shots, and Jason Kidd had three points, three assists and four rebounds before getting ejected with 7:16 left for a flagrant foul on Jannero Pargo. A fan was also ejected in owner Mark Cuban's row.&lt;/p&gt;              &lt;p&gt;Coach Avery Johnson's Mavericks went from scoring 30 points in the first quarter to 40 in the entire second half.&lt;/p&gt;              &lt;p&gt;"I don't really have an answer for it," said Nowitzki, exhaling loudly and running his hand through his hair in frustration. "All season long, we've lost leads way too quick. . . . Everybody has to be in attack mode. You have to make shots to win in this league."&lt;/p&gt;              &lt;p&gt;Phoenix 105, San Antonio 86 -- A Frenchman put the Suns on the brink of elimination, another brought the Suns back to life.&lt;/p&gt;              &lt;p&gt;Boris Diaw, starting in place of Grant Hill (abdominal strain), had 20 points, 10 rebounds and eight assists to help the Suns avoid a first-round sweep in the series, which the Spurs now lead, 3-1.&lt;/p&gt;              &lt;p&gt;"I trust him. I always have," Suns Coach Mike D'Antoni said. "I think he's a heck of a basketball player. He's been maligned here a little bit, but he can play. He stepped up big."&lt;/p&gt;              &lt;p&gt;Diaw also played tough defense on his good friend and fellow Frenchman Tony Parker, who scored 18 points after 41 in San Antonio's 115-99 victory Friday in Game 3.&lt;/p&gt;              &lt;p&gt;"I think they kind of relaxed being up 3-0," Diaw said, "but we came out and played too. We didn't come out like the series was over. We came out fired up."&lt;/p&gt;              &lt;p&gt;No one was more aggressive than Raja Bell, who scored 21 of his 27 points in a dominant first half to help Phoenix bring a one-sided end to the defending NBA champions' nine-game playoff winning streak.&lt;/p&gt;              &lt;p&gt;"We didn't expect to sweep these guys," said the Spurs' Tim Duncan, who scored 14 points. "We're excited in the situation we're in, up 3-1. We've got to win one more game, and we get to go home and try to win it there."&lt;/p&gt;              &lt;p&gt;Credit: From the Associated Press&lt;/p&gt;              &lt;div&gt;&lt;object class="mstar_text_entity"&gt;&lt;param name="pq_source" value="csx"/&gt;&lt;param name="pq_etype" value="41"/&gt;&lt;param name="mstar_entity_inline" value="N"/&gt;&lt;param name="mstar_entity_type" value="Illustration"/&gt;&lt;div class="Illustration_content"&gt;&lt;p&gt;Caption: PHOTO: ON THE RISE: The Hornets' Hilton Armstrong, right, seems up to the challenge on this Dirk Nowitzki shot.; PHOTOGRAPHER:Larry W. Smith EPA&lt;/p&gt;&lt;/div&gt;&lt;/object&gt;&lt;/div&gt;            &lt;/body&gt;          &lt;/html&gt;</Text>
</TextInfo>
<DFS>
<PubFrosting>
<Title>Los Angeles Times</Title>
<MpubId>46999</MpubId>
<SortTitle>Los Angeles Times</SortTitle>
<Qualifier>Los Angeles, Calif.</Qualifier>
<JournalCode>ANGE</JournalCode>
<SourceType>Newspapers</SourceType>
<StartDate>18860101</StartDate>
<EndDate>99991231</EndDate>
<publisher>
<PublisherName>Los Angeles Times Communications LLC</PublisherName>
<PublisherAddress>
<City>Los Angeles</City>
<Province>CA</Province>
<Country>United States</Country>
</PublisherAddress>
</publisher>
<Locators>
<Locator Type="PQPMID">
<Name>7683</Name>
</Locator>
<Locator Type="ISSN">
<Name>04583035</Name>
</Locator>
</Locators>
<CatalogNum>60200.00</CatalogNum>
<Languages>
<Language>eng</Language>
</Languages>
<Flags>
<Flag Type="BLOCK_BY_PUB">N</Flag>
<Flag Type="ARTICLE_TRANSLATION">N</Flag>
<Flag Type="ALERTING_FLAG">Y</Flag>
<Flag Type="DOC_USAGE_ROYALTIES">N</Flag>
<Flag Type="UNSTRUCTURED_DATA">N</Flag>
<Flag Type="PRIMARY_SOURCE_FLAG">N</Flag>
<Flag Type="OPEN_LAYER_RIGHTS">OL_IN_ALL</Flag>
<Flag Type="OL_CRAWL_BLOCKED">N</Flag>
<Flag Type="EXCLUDE_FROM_TDM">N</Flag>
<Flag Type="EXCLUDE_FROM_GOOGLE_SCHOLAR">N</Flag>
<Flag Type="INCLUDE_IN_PAC">N</Flag>
</Flags>
<Subjects>
<Subject>General Interest Periodicals--United States</Subject>
</Subjects>
<CurrentTitle>
<Title>Los Angeles Times</Title>
<SortTitle>Los Angeles Times</SortTitle>
<Qualifier>Los Angeles, Calif.</Qualifier>
<EndIssueDate>99991231</EndIssueDate>
<Locators>
<Locator Type="PQPMID">
<Name>7683</Name>
</Locator>
<Locator Type="ISSN">
<Name>04583035</Name>
</Locator>
</Locators>
<CatalogNum>60200.00</CatalogNum>
</CurrentTitle>
<PubHistory>
<History>
<Title>Los Angeles Daily Times</Title>
<Qualifier>Los Angeles, Calif.</Qualifier>
<EndIssueDate>18861022</EndIssueDate>
<CatalogNum>60200.A0</CatalogNum>
</History>
</PubHistory>
<CoverImageType>None</CoverImageType>
<BrowseType>IssueDateBrowse</BrowseType>
<EmbargoDays>0</EmbargoDays>
<HasGaps>0</HasGaps>
<CoverageRange>
<AlphaStartDate>Dec 4, 1996</AlphaStartDate>
<AlphaEndDate>Current</AlphaEndDate>
<NumericStartDate>19961204</NumericStartDate>
<NumericEndDate>99990101</NumericEndDate>
</CoverageRange>
<PubFrequencies/>
<ContentModel>CM_DEFAULT</ContentModel>
</PubFrosting>
<GroupFrosting>
<AlphaDate>Apr 28, 2008</AlphaDate>
<StartDate>2008-04-28</StartDate>
<EndDate>2008-04-28</EndDate>
<Locators>
<Locator Type="PQPCID">
<Name>39005911</Name>
</Locator>
</Locators>
</GroupFrosting>
</DFS>
<processed>
<is_economic>0.2613</is_economic>
<tf_idf>[('points', 0.3021), ('diaw', 0.2602), ('suns', 0.2422), ('mavericks', 0.2419), ('nowitzki', 0.2137), ('game', 0.1981), ('hornets', 0.1847), ('scored', 0.1416), ('frenchman', 0.1404), ('rebounds', 0.1342), ('dirk', 0.1307), ('ejected', 0.1215), ('spurs', 0.1145), ('brink', 0.1142), ('sweep', 0.1006), ('frustration', 0.095), ('help', 0.0934), ('phoenix', 0.0931), ('victory', 0.0927), ('orleans', 0.0919), ('assists', 0.0907), ('jannero', 0.0903), ('coach', 0.0898), ('antonio', 0.0879), ('pargo', 0.0868), ('series', 0.0863), ('exhaling', 0.0862), ('played', 0.0859), ('west', 0.0851), ('dallas', 0.0846), ('aggressive', 0.0841), ('win', 0.0834), ('14', 0.082), ('jason', 0.0801), ('scoring', 0.0794), ('half', 0.0784), ('said', 0.0782), ('shots', 0.0772), ('raja', 0.0758), ('quick', 0.0754), ('didn', 0.0739), ('antoni', 0.0736), ('came', 0.0733), ('20', 0.0701), ('pent', 0.0693), ('flagrant', 0.0692), ('maligned', 0.0685), ('abdominal', 0.0661), ('second', 0.0661), ('round', 0.0655), ('kidd', 0.0651), ('winning', 0.0635), ('avery', 0.0617), ('san', 0.0606), ('loudly', 0.0588), ('epa', 0.0586), ('boris', 0.0585), ('byron', 0.0581), ('heck', 0.0564), ('elimination', 0.0563), ('sided', 0.056), ('lead', 0.0556), ('16', 0.0556), ('armstrong', 0.0555), ('hilton', 0.0555), ('stirring', 0.0554), ('cuban', 0.0549), ('relaxed', 0.0533), ('duncan', 0.0532), ('115', 0.0529), ('mode', 0.0524), ('105', 0.0511), ('strain', 0.0505), ('parker', 0.0496), ('play', 0.0495), ('season', 0.0495), ('early', 0.0492), ('banking', 0.0491), ('foul', 0.0489), ('dominant', 0.0487), ('exit', 0.0477), ('97', 0.0476), ('champions', 0.0475), ('86', 0.0473), ('eliminate', 0.0472), ('ve', 0.047), ('big', 0.0469), ('84', 0.0467), ('come', 0.046), ('terry', 0.0458), ('bell', 0.0454), ('josh', 0.0453), ('excited', 0.044), ('think', 0.044), ('defending', 0.0438), ('hadn', 0.0436), ('tries', 0.0436), ('stepped', 0.0435), ('nba', 0.0432), ('hardly', 0.043), ('streak', 0.0419), ('larry', 0.0418), ('99', 0.0417), ('playoff', 0.0416), ('hair', 0.0413), ('grant', 0.0412), ('stretch', 0.0411), ('howard', 0.0411), ('fan', 0.0404), ('pull', 0.0403), ('tim', 0.0402), ('row', 0.0401), ('determined', 0.0398), ('leads', 0.0395), ('41', 0.0394), ('tony', 0.0394), ('trust', 0.0393), ('way', 0.0391), ('1998', 0.0389), ('10', 0.0386), ('fired', 0.0386), ('meant', 0.0381), ('trouble', 0.038), ('basketball', 0.0377), ('fellow', 0.0377), ('shooting', 0.0372), ('everybody', 0.037), ('hill', 0.0367), ('johnson', 0.0363), ('rise', 0.0362), ('avoid', 0.036), ('smith', 0.036), ('western', 0.0358), ('poor', 0.0358), ('scott', 0.0358), ('word', 0.0356), ('answer', 0.0355), ('entire', 0.0353), ('challenge', 0.0353), ('guys', 0.0352), ('straight', 0.0351), ('tough', 0.035), ('attack', 0.0349), ('january', 0.0348), ('owner', 0.0347), ('expect', 0.0346), ('situation', 0.0343), ('quarter', 0.0339), ('friend', 0.0337), ('mind', 0.033), ('mike', 0.0325), ('bit', 0.0324), ('starting', 0.0321), ('brought', 0.032), ('27', 0.032), ('player', 0.0318), ('means', 0.0316), ('effort', 0.0315), ('conference', 0.0315), ('defense', 0.0313), ('league', 0.0311), ('bring', 0.0307), ('shot', 0.0306), ('hand', 0.0305), ('wasn', 0.0305), ('new', 0.0304), ('22', 0.0304), ('mark', 0.0302), ('21', 0.03), ('photographer', 0.0296), ('24', 0.0293), ('try', 0.0293), ('running', 0.0292), ('david', 0.0289), ('40', 0.0288), ('let', 0.0282), ('seven', 0.028), ('kind', 0.0278), ('18', 0.0275), ('lost', 0.0273), ('13', 0.0272), ('getting', 0.0271), ('sunday', 0.027), ('went', 0.0262), ('tuesday', 0.026), ('start', 0.0259), ('friday', 0.0256), ('away', 0.0248), ('really', 0.0243), ('night', 0.0241), ('set', 0.024), ('got', 0.024), ('won', 0.024), ('place', 0.0238), ('days', 0.0238), ('life', 0.0237), ('best', 0.023), ('end', 0.023), ('little', 0.023), ('30', 0.0227), ('left', 0.0221), ('caption', 0.0217), ('right', 0.0215), ('good', 0.021), ('going', 0.0208), ('long', 0.0204), ('photo', 0.0203), ('home', 0.0201), ('don', 0.02), ('make', 0.019), ('like', 0.0173)]</tf_idf>
<roberta_title_negative>0.0003</roberta_title_negative>
<roberta_title_neutral>0.9988</roberta_title_neutral>
<roberta_title_positive>0.0009</roberta_title_positive>
<roberta_paragraph_positive>0.023726666666666663</roberta_paragraph_positive>
<roberta_paragraph_neutral>0.7923266666666666</roberta_paragraph_neutral>
<roberta_paragraph_negative>0.18395333333333336</roberta_paragraph_negative>
<bert_paragraph_positive>0.7646</bert_paragraph_positive>
<bert_paragraph_negative>0.2354</bert_paragraph_negative>
</processed>
</RECORD>